marbl.py
__pycache__/marbl.cpython-34.pyc
marbl_python-2.0.3.dist-info/METADATA
marbl_python-2.0.3.dist-info/metadata.json
marbl_python-2.0.3.dist-info/DESCRIPTION.rst
marbl_python-2.0.3.dist-info/top_level.txt
marbl_python-2.0.3.dist-info/RECORD
marbl_python-2.0.3.dist-info/WHEEL
