Metadata-Version: 2.0
Name: marbl-python
Version: 2.0.3
Summary: A Python implementation of the Marbl specification for normalized representations of Markov blankets in Bayesian networks.
Home-page: https://github.com/wmayner/marbl-python
Author: Will Mayner
Author-email: wmayner@gmail.com
License: GNU General Public License v3.0
Platform: UNKNOWN
Classifier: Development Status :: 3 - Alpha
Classifier: Intended Audience :: Developers
Classifier: Natural Language :: English
Classifier: License :: OSI Approved :: GNU General Public License v3 or later (GPLv3+)
Classifier: Programming Language :: Python
Classifier: Programming Language :: Python :: 3
Classifier: Programming Language :: Python :: 3.3
Classifier: Programming Language :: Python :: 3.4
Classifier: Topic :: Scientific/Engineering
Requires-Dist: msgpack-python (>=0.4.2,<1.0.0)
Requires-Dist: numpy (>=1.8.1,<2.0.0)
